LICENSE
osv/__init__.py
osv/api.py
osv/exception.py
osv/model.py
osv/py.typed
osv/serializer.py
osv_lib-0.2.1.dist-info/LICENSE
osv_lib-0.2.1.dist-info/WHEEL
osv_lib-0.2.1.dist-info/METADATA
osv_lib-0.2.1.dist-info/RECORD
