Metadata-Version: 2.1
Name: osv-lib
Version: 0.2.1
Summary: A library for querying OSV (https://osv.dev) distributed vulnerability database.
Keywords: osv,vulnerability,vulnerability-database
Author: Paul Horton
Author-email: paul.horton@owasp.org
Maintainer: Paul Horton
Maintainer-email: paul.horton@owasp.org
Requires-Python: >=3.6,<4.0
Classifier: Development Status :: 2 - Pre-Alpha
Classifier: Intended Audience :: Developers
Classifier: Intended Audience :: Information Technology
Classifier: Intended Audience :: System Administrators
Classifier: License :: OSI Approved :: Apache Software License
Classifier: Programming Language :: Python :: 3
Classifier: Programming Language :: Python :: 3.10
Classifier: Programming Language :: Python :: 3.6
Classifier: Programming Language :: Python :: 3.7
Classifier: Programming Language :: Python :: 3.8
Classifier: Programming Language :: Python :: 3.9
Classifier: Topic :: Security
Classifier: Topic :: Software Development
Classifier: Topic :: System :: Software Distribution
Classifier: Typing :: Typed
Requires-Dist: importlib-metadata (>=3.4); python_version < "3.8"
Requires-Dist: packageurl-python (>=0.9.0,<0.10.0)
Requires-Dist: requests (>=2.20.0,<3.0.0)
Requires-Dist: types-requests (>=2.25.1,<3.0.0)
Project-URL: Bug Tracker, https://github.com/madpah/osv-lib/issues
